smis/__init__.py
smis-0.0.1.dist-info/LICENSE
smis-0.0.1.dist-info/METADATA
smis-0.0.1.dist-info/WHEEL
smis-0.0.1.dist-info/top_level.txt
smis-0.0.1.dist-info/RECORD
