Metadata-Version: 2.1
Name: smis
Version: 0.0.1
Summary: Serverless microservices is smis
Home-page: https://github.com/zhammer/smis
Author: Zach Hammer
Author-email: zach.the.hammer@gmail.com
License: MIT License
Platform: UNKNOWN
